pyunit_address/__init__.py
pyunit_address/address.bz2
pyunit_address/address.py
pyunit_address/addressType.py
pyunit_address/correctionAddress.py
pyunit_address/findAddress.py
pyunit_address/hot.zip
pyunit_address/multitree.py
pyunit_address/supplementAddress.py
pyunit_address/tool.py
pyunit_address-2021.3.31.dist-info/METADATA
pyunit_address-2021.3.31.dist-info/WHEEL
pyunit_address-2021.3.31.dist-info/top_level.txt
pyunit_address-2021.3.31.dist-info/zip-safe
pyunit_address-2021.3.31.dist-info/RECORD
