Metadata-Version: 2.1
Name: pyunit-address
Version: 2021.3.31
Summary: 全国五级地址查询
Home-page: https://github.com/PyUnit/pyunit-address
Author: Jtyoui
Author-email: jtyoui@qq.com
License: MIT Licence
Platform: any
Classifier: Programming Language :: Python :: 3
Classifier: License :: OSI Approved :: MIT License
Classifier: Operating System :: OS Independent
Requires-Dist: pyahocorasick
